ucloud_common/__init__.py
ucloud_common/helpers.py
ucloud_common/host.py
ucloud_common/request.py
ucloud_common/vm.py
ucloud_common-0.5.4.dist-info/LICENSE
ucloud_common-0.5.4.dist-info/METADATA
ucloud_common-0.5.4.dist-info/WHEEL
ucloud_common-0.5.4.dist-info/top_level.txt
ucloud_common-0.5.4.dist-info/RECORD
